AUTHOR.txt
CHANGES.txt
LICENSE.txt
README.txt
TODOS.txt
bootstrap.py
buildout.cfg
setup.py
bin/buildout
bin/test
src/z3c/__init__.py
src/z3c.referercredentials.egg-info/PKG-INFO
src/z3c.referercredentials.egg-info/SOURCES.txt
src/z3c.referercredentials.egg-info/dependency_links.txt
src/z3c.referercredentials.egg-info/namespace_packages.txt
src/z3c.referercredentials.egg-info/not-zip-safe
src/z3c.referercredentials.egg-info/requires.txt
src/z3c.referercredentials.egg-info/top_level.txt
src/z3c/referercredentials/README.txt
src/z3c/referercredentials/__init__.py
src/z3c/referercredentials/credentials.py
src/z3c/referercredentials/interfaces.py
src/z3c/referercredentials/tests.py
